deezer_api/__init__.py
deezer_api/deezer.py
deezer_api-1.0.0.dist-info/LICENSE
deezer_api-1.0.0.dist-info/METADATA
deezer_api-1.0.0.dist-info/WHEEL
deezer_api-1.0.0.dist-info/top_level.txt
deezer_api-1.0.0.dist-info/RECORD
