Metadata-Version: 2.1
Name: deezer_api
Version: 1.0.0
Summary: A simple Python wrapper for the Deezer API
Home-page: https://github.com/Andryerics/deezer_api
Author: Andry RL
Author-email: andryerics@gmail.com
License: MIT
Classifier: Programming Language :: Python :: 3
Classifier: License :: OSI Approved :: MIT License
Classifier: Operating System :: OS Independent
Requires-Python: >=3.6
License-File: LICENSE
Requires-Dist: requests
